drapery/__init__.py
drapery/cli/__init__.py
drapery/cli/drape.py
drapery/cli/drape.sync-conflict-20160812-140337.py
drapery/core/__init__.py
drapery/core/api.py
drapery/core/sample.py
drapery/ops/__init__.py
drapery/ops/drape.py
drapery/ops/sample.py
drapery/ops/sample.sync-conflict-20160812-140646.py
drapery-0.0.2.dist-info/DESCRIPTION.rst
drapery-0.0.2.dist-info/METADATA
drapery-0.0.2.dist-info/RECORD
drapery-0.0.2.dist-info/WHEEL
drapery-0.0.2.dist-info/entry_points.txt
drapery-0.0.2.dist-info/metadata.json
drapery-0.0.2.dist-info/top_level.txt
