Metadata-Version: 2.0
Name: drapery
Version: 0.0.2
Summary: Python library and CLI tool to convert 2D geometries to 3D given an elevation source
Home-page: http://github.com/mrahnis/drapery
Author: Michael Rahnis
Author-email: michael.rahnis@fandm.edu
License: BSD
Keywords: survey,conversion
Platform: UNKNOWN
Classifier: Development Status :: 3 - Alpha
Classifier: License :: OSI Approved :: BSD License
Classifier: Programming Language :: Python
Classifier: Programming Language :: Python :: 3
Classifier: Topic :: Scientific/Engineering :: GIS
Requires-Dist: click
Requires-Dist: fiona
Requires-Dist: rasterio
Requires-Dist: shapely
